1/Lab1_23_20230683_20230642/alu/alu.v
module ALU #(parameter data_width = 16) (
	input [data_width - 1 : 0] A, 
	input [data_width - 1 : 0] B, 
	input [3 : 0] FuncCode,
       	output reg [data_width - 1: 0] C,
       	output reg OverflowFlag);
// Do not use delay in your implementation.

// You can declare any variables as needed.
/*
	YOUR VARIABLE DECLARATION...
*/

reg [data_width : 0] OF;

initial begin
	C = 0;
	OverflowFlag = 0;
end   	

// TODO: You should implement the functionality of ALU!
// (HINT: Use 'always @(...) begin ... end')
/*
	YOUR ALU FUNCTIONALITY IMPLEMENTATION...
*/

always @(A or B or FuncCode) begin
    // 모든 변수 초기화 (래치 방지)
    C = 0;
    OverflowFlag = 0;

    case (FuncCode)
        4'b0000 : begin // ADD
			C = A + B;
            OverflowFlag = (A[data_width - 1] ~^ B[data_width - 1]) & (A[data_width - 1] ^ C[data_width - 1]);
		end	
		4'b0001 : begin // SUB
			C = A - B;
			OverflowFlag = (A[data_width - 1] ^ B[data_width - 1]) & (A[data_width - 1] ^ C[data_width - 1]);
		end	
        4'b0010 : C = A; // ID
        4'b0011 : C = ~A; // NOT
        4'b0100 : C = A & B; // AND
        4'b0101 : C = A | B; // OR
        4'b0110 : C = ~(A & B); // NAND
        4'b0111 : C = ~(A | B); // NOR
        4'b1000 : C = A ^ B; // XOR
        4'b1001 : C = A ~^ B; // XNOR
        4'b1010 : C = A << 1; // Logical Left Shift
        4'b1011 : C = A >> 1; // Logical Right Shift
        4'b1100 : C = A <<< 1; // Arithmetic Left Shift
        4'b1101 : C = A >>> 1; // Arithmetic Right Shift
        4'b1110 : C = ~A + 1; // Two's Complement
        4'b1111 : C = 0; // Zero
        default: C = 0;
    endcase
end

endmodule

1/Lab1_23_20230683_20230642/alu/waveform.vcd
$version Generated by VerilatedVcd $end
$timescale 1ps $end
 $scope module TOP $end
  $var wire 16 # A [15:0] $end
  $var wire 16 $ B [15:0] $end
  $var wire 4 % FuncCode [3:0] $end
  $var wire 16 & C [15:0] $end
  $var wire 1 ' OverflowFlag $end
  $scope module ALU $end
   $var wire 32 ( data_width [31:0] $end
   $var wire 16 # A [15:0] $end
   $var wire 16 $ B [15:0] $end
   $var wire 4 % FuncCode [3:0] $end
   $var wire 16 & C [15:0] $end
   $var wire 1 ' OverflowFlag $end
   $var wire 17 ) OF [16:0] $end
  $upscope $end
 $upscope $end
$enddefinitions $end


#0
b0000000000000001 #
b0000000000000001 $
b0000 %
b0000000000000010 &
0'
b00000000000000000000000000010000 (
b10001101101111100 )
#1
#2
#3
#4
b0001 %
b0000000000000000 &
#5
#6
b0010 %
b0000000000000001 &
#7
#8
b0011 %
b1111111111111110 &
#9
#10
b0000000000001011 #
b0000000000000101 $
b0100 %
b0000000000000001 &
#11
#12
b0101 %
b0000000000001111 &
#13
#14
b0110 %
b1111111111111110 &
#15
#16
b0111 %
b1111111111110000 &
#17
#18
b1000 %
b0000000000001110 &
#19
#20
b1001 %
b1111111111110001 &
#21
#22
b1010 %
b0000000000010110 &
#23
#24
b1011 %
b0000000000000101 &
#25
#26
b1100 %
b0000000000010110 &
#27
#28
b1101 %
b0000000000000101 &
#29
#30
b1110 %
b1111111111110101 &
#31
#32
b1111 %
b0000000000000000 &
#33
#34
b0111111111111111 #
b0000000000000001 $
b0000 %
b1000000000000000 &
1'
#35
#36
b1000000000000000 #
b0001 %
b0111111111111111 &
