1/Lab1_23_20230683_20230642/vending_machine/change_state.v
`include "vending_machine_def.v"


module change_state(clk,reset_n, current_total_nxt, input_total, output_total, return_total, i_trigger_return, wait_time, current_total);

   input clk;
   input reset_n;
   input [`kTotalBits-1:0] current_total_nxt;
   input [`kTotalBits-1:0] input_total;
   input [`kTotalBits-1:0] output_total;
   input [`kTotalBits-1:0] return_total;
   input i_trigger_return;
   input [31:0] wait_time;
   output reg [`kTotalBits-1:0] current_total;
   
   // Sequential circuit to reset or update the states
   always @(posedge clk ) begin
      if (!reset_n || i_trigger_return || wait_time == 0) begin
         // TODO: reset all states.
         current_total <= 0;
      end

      else begin
         current_total <= current_total_nxt + input_total - output_total - return_total;
         
      end
   end
endmodule

1/Lab1_23_20230683_20230642/vending_machine/calculate_current_state.v
`include "vending_machine_def.v"
   

module calculate_current_state(i_input_coin,i_select_item,clk,item_price,coin_value,current_total,
input_total, output_total, return_total,current_total_nxt,o_return_coin,o_available_item,o_output_item);
   
    input [`kNumCoins-1:0] i_input_coin,o_return_coin;
    input [`kNumItems-1:0]   i_select_item;       
    input clk;  
    input [31:0] item_price [`kNumItems-1:0];
    input [31:0] coin_value [`kNumCoins-1:0];   
    input [`kTotalBits-1:0] current_total;
    output reg [`kNumItems-1:0] o_available_item,o_output_item;
    output reg  [`kTotalBits-1:0] input_total, output_total, return_total,current_total_nxt;
    integer i;  
    reg [`kTotalBits-1:0] current_temp;

    initial begin
    	o_available_item = 0;
        input_total = 0;
        output_total = 0;
        return_total = 0;
        current_total_nxt = 0;
    end
   
    // Combinational logic for the next states
    always @(*) begin
        // TODO: current_total_nxt
        // You don't have to worry about concurrent activations in each input vector (or array).
        // Calculate the next current_total state.
		input_total = 0;
    	output_total = 0;
    	return_total = 0;

        if (i_input_coin) begin
            for(i = 0; i < `kNumCoins; i = i + 1) begin
                if (i_input_coin[i] == 1) begin
            	    input_total = input_total + coin_value[i];
                end
            end
        end

        if (i_select_item) begin
			for (i = 0; i < `kNumItems; i = i + 1) begin
				if (current_total >= i_select_item[i] * item_price[i] && i_select_item[i] == 1) begin
					output_total = output_total + item_price[i];
				end
			end
        end

        if (o_return_coin) begin
            for (i = 0; i < `kNumCoins; i = i + 1) begin
                if (o_return_coin[i] == 1) begin
                    return_total = return_total + o_return_coin[i] * coin_value[i];
                end
			end
        end

        current_total_nxt = current_total;
    end

    // Combinational logic for the outputs
    always @(*) begin
        // TODO: o_available_item
        // TODO: o_output_item
        o_available_item = 0;
        for(i = 0; i < `kNumItems ; i = i + 1) begin
            if (current_total >= item_price[i]) begin
            	o_available_item[i] = 1;
        	end
		end
    end

    always @(posedge clk) begin
        o_output_item <= 0;
        for (i = 0; i < `kNumItems; i = i + 1) begin    
            if (current_total >= i_select_item[i] * item_price[i] && i_select_item[i] == 1) begin
                o_output_item[i] <= 1;
            end
        end
    end

endmodule

1/Lab1_23_20230683_20230642/vending_machine/check_time_and_coin.v
`include "vending_machine_def.v"


module check_time_and_coin(i_input_coin,i_select_item,clk,reset_n,wait_time,o_return_coin ,item_price,coin_value,current_total,i_trigger_return);
	input clk;
	input reset_n;
	input [`kNumCoins-1:0] i_input_coin;
	input [`kNumItems-1:0]	i_select_item;
	input [31:0] item_price [`kNumItems-1:0];
	input [31:0] coin_value [`kNumCoins-1:0];
	input [`kTotalBits-1:0] current_total;
	input i_trigger_return;
	output reg [`kNumCoins-1:0] o_return_coin;
	output reg [31:0] wait_time;

	reg [`kTotalBits-1:0] coin_required;
	reg [`kTotalBits-1:0] remaining_total;
	reg [`kNumCoins-1:0] nxt_return_coin;

	// initiate values
	initial begin
		// TODO: initiate values
		o_return_coin = 0;
		wait_time = `kWaitTime;
	end



	always @(*) begin
		// TODO: o_return_coin
		remaining_total = current_total;
		nxt_return_coin = o_return_coin;
		if (!reset_n) begin
			// TODO: reset all states.
			nxt_return_coin = 0;
		end

		else if (wait_time == 0 || i_trigger_return) begin
			for (int i = `kNumCoins-1; i >= 0; i = i - 1) begin
            	if (remaining_total >= coin_value[i]) begin
            	    nxt_return_coin[i] = 1;
            	    remaining_total = remaining_total - coin_value[i];
            	end
       		end
		end

	end

	always @(posedge clk ) begin
		// TODO: reset all states.
		if (!reset_n) begin
			o_return_coin <= 0;
			wait_time <= `kWaitTime;
		end

		else begin
			o_return_coin <= nxt_return_coin;

			// TODO: update coin return time
			if (i_input_coin) begin
				wait_time <= `kWaitTime;
			end
		
			else if (i_select_item) begin
				coin_required = 0;
				for (int i = 0; i < `kNumItems; i += 1) begin
					coin_required += i_select_item[i] * item_price[i];
				end
				if (current_total >= coin_required) begin
					wait_time <= `kWaitTime;
				end
			end

			else if (wait_time > 0) begin
				// TODO: update all states.
				wait_time <= wait_time - 1;
			end
		end
	end
endmodule

1/Lab1_23_20230683_20230642/vending_machine/vending_machine.v
// Title         : vending_machine.v
// Author      : Jae-Eon Jo (Jojaeeon@postech.ac.kr) 
//			     Dongup Kwon (nankdu7@postech.ac.kr) (2015.03.30)
//			     Jaehun Ryu (jaehunryu@postech.ac.kr) (2021.03.07)

`include "vending_machine_def.v"


module vending_machine (
	clk,							// Clock signal
	reset_n,						// Reset signal (active-low)

	i_input_coin,				// coin is inserted.
	i_select_item,				// item is selected.
	i_trigger_return,			// change-return is triggered 

	o_available_item,			// Sign of the item availability
	o_output_item,			// Sign of the item withdrawal
	o_return_coin				// Sign of the coin return
);

	// Ports Declaration
	// Do not modify the module interface
	input clk;
	input reset_n;
	
	input [`kNumCoins-1:0] i_input_coin;
	input [`kNumItems-1:0] i_select_item;
	input i_trigger_return;
		
	output [`kNumItems-1:0] o_available_item;
	output [`kNumItems-1:0] o_output_item;
	output [`kNumCoins-1:0] o_return_coin;


	

	// Do not modify the values.
	wire [31:0] item_price [`kNumItems-1:0];	// Price of each item
	wire [31:0] coin_value [`kNumCoins-1:0];	// Value of each coin
	assign item_price[0] = 400;
	assign item_price[1] = 500;
	assign item_price[2] = 1000;
	assign item_price[3] = 2000;
	assign coin_value[0] = 100;
	assign coin_value[1] = 500;
	assign coin_value[2] = 1000;

	// Internal states. You may add your own net variables.
	wire [`kTotalBits-1:0] current_total;
	
	// Next internal states. You may add your own net variables.
	wire [`kTotalBits-1:0] current_total_nxt;

	
	// Variables. You may add more your own net variables.
	wire [`kTotalBits-1:0] input_total, output_total, return_total;
	wire [31:0] wait_time;


	// This module interface, structure, and given a number of modules are not mandatory but recommended.
	// However, Implementations that use modules are mandatory.
		
  	check_time_and_coin check_time_and_coin_module(.i_input_coin(i_input_coin),
  									.i_select_item(i_select_item),
									.clk(clk),
									.reset_n(reset_n),
									.wait_time(wait_time),
									.o_return_coin(o_return_coin),
									.item_price(item_price),
									.coin_value(coin_value),
									.current_total(current_total),
									.i_trigger_return(i_trigger_return));

	calculate_current_state calculate_current_state_module(.i_input_coin(i_input_coin),
										.i_select_item(i_select_item),
										.clk(clk),
										.item_price(item_price),
										.coin_value(coin_value),
										.current_total(current_total),
										.input_total(input_total),
										.output_total(output_total),
										.return_total(return_total),
										.current_total_nxt(current_total_nxt),
										.o_return_coin(o_return_coin),
										.o_available_item(o_available_item),
										.o_output_item(o_output_item));
	
  	change_state change_state_module(
						.clk(clk),
						.reset_n(reset_n),
						.current_total_nxt(current_total_nxt),
						.current_total(current_total), 
						.input_total(input_total), 
						.output_total(output_total), 
						.return_total(return_total), 
						.i_trigger_return(i_trigger_return), 
						.wait_time(wait_time));


endmodule

1/Lab1_23_20230683_20230642/vending_machine/waveform.vcd
$version Generated by VerilatedVcd $end
$timescale 1ps $end
 $scope module TOP $end
  $var wire 1 5 clk $end
  $var wire 1 6 reset_n $end
  $var wire 3 7 i_input_coin [2:0] $end
  $var wire 4 8 i_select_item [3:0] $end
  $var wire 1 9 i_trigger_return $end
  $var wire 4 : o_available_item [3:0] $end
  $var wire 4 ; o_output_item [3:0] $end
  $var wire 3 < o_return_coin [2:0] $end
  $scope module vending_machine $end
   $var wire 1 5 clk $end
   $var wire 1 6 reset_n $end
   $var wire 3 7 i_input_coin [2:0] $end
   $var wire 4 8 i_select_item [3:0] $end
   $var wire 1 9 i_trigger_return $end
   $var wire 4 : o_available_item [3:0] $end
   $var wire 4 ; o_output_item [3:0] $end
   $var wire 3 < o_return_coin [2:0] $end
   $var wire 32 # item_price[0] [31:0] $end
   $var wire 32 $ item_price[1] [31:0] $end
   $var wire 32 % item_price[2] [31:0] $end
   $var wire 32 & item_price[3] [31:0] $end
   $var wire 32 ' coin_value[0] [31:0] $end
   $var wire 32 ( coin_value[1] [31:0] $end
   $var wire 32 ) coin_value[2] [31:0] $end
   $var wire 31 / current_total [30:0] $end
   $var wire 31 0 current_total_nxt [30:0] $end
   $var wire 31 = input_total [30:0] $end
   $var wire 31 * output_total [30:0] $end
   $var wire 31 1 return_total [30:0] $end
   $var wire 32 2 wait_time [31:0] $end
   $scope module calculate_current_state_module $end
    $var wire 3 7 i_input_coin [2:0] $end
    $var wire 3 < o_return_coin [2:0] $end
    $var wire 4 8 i_select_item [3:0] $end
    $var wire 1 5 clk $end
    $var wire 32 # item_price[0] [31:0] $end
    $var wire 32 $ item_price[1] [31:0] $end
    $var wire 32 % item_price[2] [31:0] $end
    $var wire 32 & item_price[3] [31:0] $end
    $var wire 32 ' coin_value[0] [31:0] $end
    $var wire 32 ( coin_value[1] [31:0] $end
    $var wire 32 ) coin_value[2] [31:0] $end
    $var wire 31 / current_total [30:0] $end
    $var wire 4 : o_available_item [3:0] $end
    $var wire 4 ; o_output_item [3:0] $end
    $var wire 31 = input_total [30:0] $end
    $var wire 31 * output_total [30:0] $end
    $var wire 31 1 return_total [30:0] $end
    $var wire 31 0 current_total_nxt [30:0] $end
    $var wire 32 + i [31:0] $end
    $var wire 31 > current_temp [30:0] $end
   $upscope $end
   $scope module change_state_module $end
    $var wire 1 5 clk $end
    $var wire 1 6 reset_n $end
    $var wire 31 0 current_total_nxt [30:0] $end
    $var wire 31 = input_total [30:0] $end
    $var wire 31 * output_total [30:0] $end
    $var wire 31 1 return_total [30:0] $end
    $var wire 1 9 i_trigger_return $end
    $var wire 32 2 wait_time [31:0] $end
    $var wire 31 / current_total [30:0] $end
   $upscope $end
   $scope module check_time_and_coin_module $end
    $var wire 1 5 clk $end
    $var wire 1 6 reset_n $end
    $var wire 3 7 i_input_coin [2:0] $end
    $var wire 4 8 i_select_item [3:0] $end
    $var wire 32 # item_price[0] [31:0] $end
    $var wire 32 $ item_price[1] [31:0] $end
    $var wire 32 % item_price[2] [31:0] $end
    $var wire 32 & item_price[3] [31:0] $end
    $var wire 32 ' coin_value[0] [31:0] $end
    $var wire 32 ( coin_value[1] [31:0] $end
    $var wire 32 ) coin_value[2] [31:0] $end
    $var wire 31 / current_total [30:0] $end
    $var wire 1 9 i_trigger_return $end
    $var wire 3 < o_return_coin [2:0] $end
    $var wire 32 2 wait_time [31:0] $end
    $var wire 31 3 coin_required [30:0] $end
    $var wire 31 , remaining_total [30:0] $end
    $var wire 3 - nxt_return_coin [2:0] $end
    $scope module unnamedblk1 $end
     $var wire 32 . i [31:0] $end
    $upscope $end
    $scope module unnamedblk2 $end
     $var wire 32 4 i [31:0] $end
    $upscope $end
   $upscope $end
  $upscope $end
 $upscope $end
$enddefinitions $end


#0
b00000000000000000000000110010000 #
b00000000000000000000000111110100 $
b00000000000000000000001111101000 %
b00000000000000000000011111010000 &
b00000000000000000000000001100100 '
b00000000000000000000000111110100 (
b00000000000000000000001111101000 )
b0000000000000000000001110000100 *
b00000000000000000000000000000100 +
b1000110010101111110111011101001 ,
b000 -
b00000000000000000000000000000000 .
b1000110010101111110111011101001 /
b1000110010101111110111011101001 0
b0000000000000000000000000000000 1
b00000000000000000000000001100100 2
b1100100100101011010110000101011 3
b00000000000000000000000000000000 4
15
06
b010 7
b0011 8
09
b1111 :
b0110 ;
b000 <
b0000000000000000000000111110100 =
b0101101100001101011001001111000 >
#1
05
16
#2
b0000000000000000000000000000000 *
b0000000000000000000000000000000 ,
b0000000000000000000000000000000 /
b0000000000000000000000000000000 0
15
06
b0000 :
b0011 ;
#3
05
#4
b00000000000000000000000001100011 2
15
16
b000 7
b0000 8
b0000 ;
b0000000000000000000000000000000 =
#5
05
#6
b00000000000000000000000001100010 2
15
#7
05
#8
b00000000000000000000000001100001 2
15
#9
05
#10
b00000000000000000000000000000011 +
b0000000000000000000000001100100 ,
b0000000000000000000000001100100 /
b0000000000000000000000001100100 0
b00000000000000000000000001100100 2
15
b001 7
b0000000000000000000000001100100 =
#11
05
b000 7
b0000000000000000000000000000000 =
#12
b0000000000000000000000011001000 ,
b0000000000000000000000011001000 /
b0000000000000000000000011001000 0
15
b001 7
b0000000000000000000000001100100 =
#13
05
b000 7
b0000000000000000000000000000000 =
#14
b0000000000000000000000100101100 ,
b0000000000000000000000100101100 /
b0000000000000000000000100101100 0
15
b001 7
b0000000000000000000000001100100 =
#15
05
b000 7
b0000000000000000000000000000000 =
#16
b0000000000000000000000110010000 ,
b0000000000000000000000110010000 /
b0000000000000000000000110010000 0
15
b001 7
b0001 :
b0000000000000000000000001100100 =
#17
05
b000 7
b0000000000000000000000000000000 =
#18
b0000000000000000000000111110100 ,
b0000000000000000000000111110100 /
b0000000000000000000000111110100 0
15
b001 7
b0011 :
b0000000000000000000000001100100 =
#19
05
b000 7
b0000000000000000000000000000000 =
#20
b0000000000000000000001001011000 ,
b0000000000000000000001001011000 /
b0000000000000000000001001011000 0
15
b001 7
b0000000000000000000000001100100 =
#21
05
b000 7
b0000000000000000000000000000000 =
#22
b0000000000000000000001010111100 ,
b0000000000000000000001010111100 /
b0000000000000000000001010111100 0
15
b001 7
b0000000000000000000000001100100 =
#23
05
b000 7
b0000000000000000000000000000000 =
#24
b0000000000000000000001100100000 ,
b0000000000000000000001100100000 /
b0000000000000000000001100100000 0
15
b001 7
b0000000000000000000000001100100 =
#25
05
b000 7
b0000000000000000000000000000000 =
#26
b0000000000000000000001110000100 ,
b0000000000000000000001110000100 /
b0000000000000000000001110000100 0
15
b001 7
b0000000000000000000000001100100 =
#27
05
b000 7
b0000000000000000000000000000000 =
#28
b0000000000000000000001111101000 ,
b0000000000000000000001111101000 /
b0000000000000000000001111101000 0
15
b001 7
b0111 :
b0000000000000000000000001100100 =
#29
05
b000 7
b0000000000000000000000000000000 =
#30
b0000000000000000000010001001100 ,
b0000000000000000000010001001100 /
b0000000000000000000010001001100 0
15
b001 7
b0000000000000000000000001100100 =
#31
05
b000 7
b0000000000000000000000000000000 =
#32
b0000000000000000000010010110000 ,
b0000000000000000000010010110000 /
b0000000000000000000010010110000 0
15
b001 7
b0000000000000000000000001100100 =
#33
05
b000 7
b0000000000000000000000000000000 =
#34
b0000000000000000000010100010100 ,
b0000000000000000000010100010100 /
b0000000000000000000010100010100 0
15
b001 7
b0000000000000000000000001100100 =
#35
05
b000 7
b0000000000000000000000000000000 =
#36
b0000000000000000000010101111000 ,
b0000000000000000000010101111000 /
b0000000000000000000010101111000 0
15
b001 7
b0000000000000000000000001100100 =
#37
05
b000 7
b0000000000000000000000000000000 =
#38
b0000000000000000000010111011100 ,
b0000000000000000000010111011100 /
b0000000000000000000010111011100 0
15
b001 7
b0000000000000000000000001100100 =
#39
05
b000 7
b0000000000000000000000000000000 =
#40
b0000000000000000000011001000000 ,
b0000000000000000000011001000000 /
b0000000000000000000011001000000 0
15
b001 7
b0000000000000000000000001100100 =
#41
05
b000 7
b0000000000000000000000000000000 =
#42
b0000000000000000000011010100100 ,
b0000000000000000000011010100100 /
b0000000000000000000011010100100 0
15
b001 7
b0000000000000000000000001100100 =
#43
05
b000 7
b0000000000000000000000000000000 =
#44
b0000000000000000000011100001000 ,
b0000000000000000000011100001000 /
b0000000000000000000011100001000 0
15
b001 7
b0000000000000000000000001100100 =
#45
05
b000 7
b0000000000000000000000000000000 =
#46
b0000000000000000000011101101100 ,
b0000000000000000000011101101100 /
b0000000000000000000011101101100 0
15
b001 7
b0000000000000000000000001100100 =
#47
05
b000 7
b0000000000000000000000000000000 =
#48
b0000000000000000000011111010000 ,
b0000000000000000000011111010000 /
b0000000000000000000011111010000 0
15
b001 7
b1111 :
b0000000000000000000000001100100 =
#49
05
b000 7
b0000000000000000000000000000000 =
#50
b00000000000000000000000000000100 +
b00000000000000000000000001100011 2
15
#51
05
#52
b0000000000000000000000000000000 ,
b0000000000000000000000000000000 /
b0000000000000000000000000000000 0
b00000000000000000000000001100100 2
15
06
b0000 :
#53
b00000000000000000000000000000011 +
05
16
b001 7
b0000000000000000000000001100100 =
#54
b0000000000000000000000001100100 ,
b0000000000000000000000001100100 /
b0000000000000000000000001100100 0
15
#55
b0000000000000000000000000000000 ,
b001 -
b11111111111111111111111111111111 .
05
b000 7
19
b0000000000000000000000000000000 =
#56
b0000000000000000000000000000000 /
b0000000000000000000000000000000 0
b0000000000000000000000001100100 1
b00000000000000000000000001100011 2
15
b001 <
#57
05
#58
b00000000000000000000000001100010 2
15
#59
05
#60
b00000000000000000000000001100001 2
15
#61
05
09
#62
b00000000000000000000000000000100 +
b000 -
b0000000000000000000000000000000 1
b00000000000000000000000001100100 2
15
06
b000 <
#63
b00000000000000000000000000000011 +
05
16
b010 7
b0000000000000000000000111110100 =
#64
b0000000000000000000000111110100 ,
b0000000000000000000000111110100 /
b0000000000000000000000111110100 0
15
b0011 :
#65
b0000000000000000000000000000000 ,
b010 -
05
b000 7
19
b0000000000000000000000000000000 =
#66
b0000000000000000000000000000000 /
b0000000000000000000000000000000 0
b0000000000000000000000111110100 1
b00000000000000000000000001100011 2
15
b0000 :
b010 <
#67
05
#68
b00000000000000000000000001100010 2
15
#69
05
#70
b00000000000000000000000001100001 2
15
#71
05
09
#72
b00000000000000000000000000000100 +
b000 -
b0000000000000000000000000000000 1
b00000000000000000000000001100100 2
15
06
b000 <
#73
b00000000000000000000000000000011 +
05
16
b100 7
b0000000000000000000001111101000 =
#74
b0000000000000000000001111101000 ,
b0000000000000000000001111101000 /
b0000000000000000000001111101000 0
15
b0111 :
#75
b0000000000000000000000000000000 ,
b100 -
05
b000 7
19
b0000000000000000000000000000000 =
#76
b0000000000000000000000000000000 /
b0000000000000000000000000000000 0
b0000000000000000000001111101000 1
b00000000000000000000000001100011 2
15
b0000 :
b100 <
#77
05
#78
b00000000000000000000000001100010 2
15
#79
05
#80
b00000000000000000000000001100001 2
15
#81
05
09
#82
b00000000000000000000000000000100 +
b000 -
b0000000000000000000000000000000 1
b00000000000000000000000001100100 2
15
06
b000 <
#83
b00000000000000000000000000000011 +
05
16
b011 7
b0000000000000000000001001011000 =
#84
b0000000000000000000001001011000 ,
b0000000000000000000001001011000 /
b0000000000000000000001001011000 0
15
b0011 :
#85
b0000000000000000000000000000000 ,
b011 -
05
b000 7
19
b0000000000000000000000000000000 =
#86
b0000000000000000000000000000000 /
b0000000000000000000000000000000 0
b0000000000000000000001001011000 1
b00000000000000000000000001100011 2
15
b0000 :
b011 <
#87
05
#88
b00000000000000000000000001100010 2
15
#89
05
#90
b00000000000000000000000001100001 2
15
#91
05
09
#92
b00000000000000000000000000000100 +
b000 -
b0000000000000000000000000000000 1
b00000000000000000000000001100100 2
15
06
b000 <
#93
b00000000000000000000000000000011 +
05
16
b101 7
b0000000000000000000010001001100 =
#94
b0000000000000000000010001001100 ,
b0000000000000000000010001001100 /
b0000000000000000000010001001100 0
15
b0111 :
#95
b0000000000000000000000000000000 ,
b101 -
05
b000 7
19
b0000000000000000000000000000000 =
#96
b0000000000000000000000000000000 /
b0000000000000000000000000000000 0
b0000000000000000000010001001100 1
b00000000000000000000000001100011 2
15
b0000 :
b101 <
#97
05
#98
b00000000000000000000000001100010 2
15
#99
05
#100
b00000000000000000000000001100001 2
15
#101
05
09
#102
b00000000000000000000000000000100 +
b000 -
b0000000000000000000000000000000 1
b00000000000000000000000001100100 2
15
06
b000 <
#103
b00000000000000000000000000000011 +
05
16
b110 7
b0000000000000000000010111011100 =
#104
b0000000000000000000010111011100 ,
b0000000000000000000010111011100 /
b0000000000000000000010111011100 0
15
b0111 :
#105
b0000000000000000000000000000000 ,
b110 -
05
b000 7
19
b0000000000000000000000000000000 =
#106
b0000000000000000000000000000000 /
b0000000000000000000000000000000 0
b0000000000000000000010111011100 1
b00000000000000000000000001100011 2
15
b0000 :
b110 <
#107
05
#108
b00000000000000000000000001100010 2
15
#109
05
#110
b00000000000000000000000001100001 2
15
#111
05
09
#112
b00000000000000000000000000000100 +
b000 -
b0000000000000000000000000000000 1
b00000000000000000000000001100100 2
15
06
b000 <
#113
b00000000000000000000000000000011 +
05
16
b111 7
b0000000000000000000011001000000 =
#114
b0000000000000000000011001000000 ,
b0000000000000000000011001000000 /
b0000000000000000000011001000000 0
15
b0111 :
#115
b0000000000000000000000000000000 ,
b111 -
05
b000 7
19
b0000000000000000000000000000000 =
#116
b0000000000000000000000000000000 /
b0000000000000000000000000000000 0
b0000000000000000000011001000000 1
b00000000000000000000000001100011 2
15
b0000 :
b111 <
#117
05
#118
b00000000000000000000000001100010 2
15
#119
05
#120
b00000000000000000000000001100001 2
15
#121
05
09
#122
b00000000000000000000000000000100 +
b000 -
b0000000000000000000000000000000 1
b00000000000000000000000001100100 2
15
06
b000 <
#123
b00000000000000000000000000000011 +
05
16
b111 7
b0000000000000000000011001000000 =
#124
b0000000000000000000011001000000 ,
b0000000000000000000011001000000 /
b0000000000000000000011001000000 0
15
b0111 :
#125
05
b000 7
b0000000000000000000000000000000 =
#126
b00000000000000000000000000000100 +
b0000000000000000000000001100100 ,
b0000000000000000000000001100100 /
b0000000000000000000000001100100 0
b0000000000000000000010111011100 3
b00000000000000000000000000000100 4
15
b0110 8
b0000 :
b0110 ;
#127
05
b0000 8
#128
b00000000000000000000000001100011 2
15
b0000 ;
#129
05
#130
b00000000000000000000000001100010 2
15
#131
05
#132
b00000000000000000000000001100001 2
15
#133
05
#134
b00000000000000000000000001100000 2
15
#135
05
#136
b00000000000000000000000001011111 2
15
#137
05
#138
b00000000000000000000000001011110 2
15
#139
05
#140
b00000000000000000000000001011101 2
15
#141
05
#142
b00000000000000000000000001011100 2
15
#143
05
#144
b00000000000000000000000001011011 2
15
#145
05
#146
b00000000000000000000000001011010 2
15
#147
05
#148
b00000000000000000000000001011001 2
15
#149
05
#150
b00000000000000000000000001011000 2
15
#151
05
#152
b00000000000000000000000001010111 2
15
#153
05
#154
b00000000000000000000000001010110 2
15
#155
05
#156
b00000000000000000000000001010101 2
15
#157
05
#158
b00000000000000000000000001010100 2
15
#159
05
#160
b00000000000000000000000001010011 2
15
#161
05
#162
b00000000000000000000000001010010 2
15
#163
05
#164
b00000000000000000000000001010001 2
15
#165
05
#166
b00000000000000000000000001010000 2
15
#167
05
#168
b00000000000000000000000001001111 2
15
#169
05
#170
b00000000000000000000000001001110 2
15
#171
05
#172
b00000000000000000000000001001101 2
15
#173
05
#174
b00000000000000000000000001001100 2
15
#175
05
#176
b00000000000000000000000001001011 2
15
#177
05
#178
b00000000000000000000000001001010 2
15
#179
05
#180
b00000000000000000000000001001001 2
15
#181
05
#182
b00000000000000000000000001001000 2
15
#183
05
#184
b00000000000000000000000001000111 2
15
#185
05
#186
b00000000000000000000000001000110 2
15
#187
05
#188
b00000000000000000000000001000101 2
15
#189
05
#190
b00000000000000000000000001000100 2
15
#191
05
#192
b00000000000000000000000001000011 2
15
#193
05
#194
b00000000000000000000000001000010 2
15
#195
05
#196
b00000000000000000000000001000001 2
15
#197
05
#198
b00000000000000000000000001000000 2
15
